niksms/Service_pb2.py
niksms/Service_pb2_grpc.py
niksms/__init__.py
niksms/grpc.py
niksms/rest.py
niksms-1.2.0.dist-info/METADATA
niksms-1.2.0.dist-info/WHEEL
niksms-1.2.0.dist-info/top_level.txt
niksms-1.2.0.dist-info/RECORD
