Metadata-Version: 2.4
Name: Niksms
Version: 1.2.0
Summary: niksms webservice
Home-page: https://webservice.niksms.com
Author: Kendez
Author-email: Niksms <info@niksms.com>
Classifier: Programming Language :: Python :: 3
Classifier: License :: OSI Approved :: MIT License
Classifier: Operating System :: OS Independent
Requires-Python: >=3.7
Requires-Dist: requests
Requires-Dist: grpcio
Requires-Dist: protobuf
Dynamic: author
Dynamic: home-page
Dynamic: requires-python
